videoframes/__init__.py
videoframes/frames.py
videoframes-0.0.4.data/scripts/videoframes
videoframes-0.0.4.dist-info/LICENSE
videoframes-0.0.4.dist-info/METADATA
videoframes-0.0.4.dist-info/WHEEL
videoframes-0.0.4.dist-info/top_level.txt
videoframes-0.0.4.dist-info/RECORD
