Metadata-Version: 2.1
Name: videoframes
Version: 0.0.4
Summary: Extract/assemble frame images from/to a video file
Home-page: https://gitlab.com/jspiers/videoframes
Author: Jeffrey Spiers
Author-email: jeffrey.spiers@mail.mcgill.ca
License: UNKNOWN
Platform: UNKNOWN
Classifier: Programming Language :: Python :: 3
Classifier: License :: OSI Approved :: MIT License
Classifier: Operating System :: OS Independent
Requires-Python: >=3.5
Requires-Dist: tqdm (>=2.0.0)
Requires-Dist: opencv-contrib-python (>=3.4.2.16)
